epicsdevtektronixmso/__init__.py
epicsdevtektronixmso/__main__.py
epicsdevtektronixmso/mainModule.py
epicsdevtektronixmso-0.1.2.dist-info/METADATA
epicsdevtektronixmso-0.1.2.dist-info/WHEEL
epicsdevtektronixmso-0.1.2.dist-info/licenses/LICENSE
epicsdevtektronixmso-0.1.2.dist-info/RECORD
