Metadata-Version: 2.4
Name: epicsdevtektronixmso
Version: 0.1.2
Summary: EPICS PVAccess server for Tektronix MSO oscilloscopes
Project-URL: Homepage, https://github.com/ASukhanov/epicsDevTektronixMSO
Project-URL: Bug Tracker, https://github.com/ASukhanov/epicsDevTektronixMSO/issues
Author-email: Andrey Sukhanov <sukhanov@bnl.gov>
License-File: LICENSE
Classifier: License :: OSI Approved :: MIT License
Classifier: Operating System :: OS Independent
Classifier: Programming Language :: Python :: 3
Requires-Python: >=3.7
Requires-Dist: p4p
Requires-Dist: pyvisa-py
